{"div":[{"no":1,"title":"cheerup", "singer":"트와이스", "nickname":"닉네임10", "heart":254, "img":"../picture/images01.PNG"},
  {"no":2,"title":"소원을 말해봐", "singer":"소녀시대", "nickname":"닉네임09", "heart":253, "img":"../picture/images02.PNG"},
  {"no":3,"title":"나를 찾아줘", "singer":"전효성", "nickname":"닉네임08", "heart":252, "img":"../picture/images03.PNG"},
  {"no":4,"title":"Hello", "singer":"허각", "nickname":"닉네임07", "heart":251, "img":"../picture/images04.PNG"},
  {"no":5,"title":"야생화", "singer":"박효신", "nickname":"닉네임06", "heart":250, "img":"../picture/images05.PNG"}]}
